Metadata-Version: 2.1
Name: orientation-observer
Version: 0.0.2
Summary: Dash Mobile Orientation Observer Component
Author: s_matsumoto <s_matsumoto@thinkup-sol.co.jp>
License: MIT
Classifier: Framework :: Dash
License-File: LICENSE
